{
  "M.G. Knoef_CentERdata": {
    "full_name": "M.G. Knoef",
    "given_name": "M.G.",
    "family_name": "Knoef",
    "orcid_id": "",
    "email": "",
    "current_position": "",
    "affiliation": "",
    "department": "",
    "institution_url": "",
    "institution_ror_id": "",
    "google_scholar_id": "",
    "citation_count": 0,
    "h_index": 0,
    "expertise_areas": [],
    "research_interests": []
  },
  "Ours, J.C. van_CentERdata": {
    "full_name": "Ours, J.C. van",
    "given_name": "Ours, J.C.",
    "family_name": "van",
    "orcid_id": "https://orcid.org/0000-0002-8863-7043",
    "email": "",
    "current_position": "",
    "affiliation": "",
    "department": "",
    "institution_url": "",
    "institution_ror_id": "",
    "google_scholar_id": "",
    "citation_count": 0,
    "h_index": 0,
    "expertise_areas": [
      "Economics"
    ],
    "research_interests": []
  }
}